{
  "timestamp": "2026-05-27T12:37:53.482Z",
  "rtCount": 3,
  "addLiqUsdc": 700,
  "swapUsdc": 500,
  "t22Bps": 1,
  "liquidityDelta": "171319360060",
  "poolLiquidity": "111283654549",
  "usdcNeeded": 699.999999,
  "hopToSend": 4777505.899876,
  "totalHopXferHop": 28976540.454184,
  "t22WithheldHop": 2897.654045,
  "t22WithheldUsdc": 0.313269,
  "lpFeeDrainProjected": 0.9,
  "gasUsdc": 0.03075,
  "cashNetProj": 0.282519,
  "cuConsumed": 707649,
  "cuLimitFinal": 778414,
  "txSize": 915,
  "simOk": true,
  "simErr": null,
  "verdict": "SIM_OK_PROFITABLE",
  "tickBefore": 91328,
  "tickFromCenter": -1192,
  "rangeUtilization": 0.4068,
  "swapDirection": "USDC_TO_HOP",
  "onchainSig": "2mwC736tH6QbwQgYFPMWxgTWGQ2Csty7SCk8pT4Jtn4wdeistSg5u7dKihFYf2a7x8iyEVExL2p2q2WwiQgyH8Bc",
  "onchainStatus": "confirmed",
  "tickAfterLive": 91331,
  "tickDriftLive": 3
}
