{
  "timestamp": "2026-05-27T15:43:51.414Z",
  "rtCount": 3,
  "addLiqUsdc": 700,
  "swapUsdc": 500,
  "t22Bps": 1,
  "liquidityDelta": "99768085780",
  "poolLiquidity": "111283654549",
  "usdcNeeded": 162.646792,
  "hopToSend": 5749370.983221,
  "totalHopXferHop": 44788014.088598,
  "t22WithheldHop": 4478.801408,
  "t22WithheldUsdc": 0.282499,
  "lpFeeDrainProjected": 0.9,
  "gasUsdc": 0.03075,
  "cashNetProj": 0.251749,
  "cuConsumed": 732810,
  "cuLimitFinal": 806092,
  "txSize": 915,
  "simOk": true,
  "simErr": null,
  "verdict": "SIM_OK_PROFITABLE",
  "tickBefore": 96716,
  "tickFromCenter": 4196,
  "rangeUtilization": 0.7269,
  "swapDirection": "USDC_TO_HOP",
  "onchainSig": "5wbgWLE6DnRickRkqy8HuUewcjXR4PBKUh6vrJze91xqPC1hd9EG19pVyMmKpaJUUGVDL9SqAoyc2rJffpVE2sk7",
  "onchainStatus": "confirmed",
  "tickAfterLive": 96722,
  "tickDriftLive": 6
}
